LICENSE
README.md
setup.cfg
setup.py
ixbrl_parse/__init__.py
ixbrl_parse/dataframe.py
ixbrl_parse/ixbrl.py
ixbrl_parse/schema.py
ixbrl_parse/transform.py
ixbrl_parse/value.py
ixbrl_parse.egg-info/PKG-INFO
ixbrl_parse.egg-info/SOURCES.txt
ixbrl_parse.egg-info/dependency_links.txt
ixbrl_parse.egg-info/requires.txt
ixbrl_parse.egg-info/top_level.txt
scripts/ixbrl-diff
scripts/ixbrl-dump
scripts/ixbrl-markdown
scripts/ixbrl-report
scripts/ixbrl-to-csv
scripts/ixbrl-to-json
scripts/ixbrl-to-kv
scripts/ixbrl-to-rdf
scripts/ixbrl-to-xbrl