Metadata-Version: 2.1
Name: ixbrl-parse
Version: 0.9.4
Summary: Parse iXBRL files, can present in RDF
Home-page: https://github.com/cybermaggedon/ixbrl-parse
Author: Cybermaggedon
Author-email: mark@cyberapocalypse.co.uk
License: UNKNOWN
Download-URL: https://github.com/cybermaggedon/ixbrl-parse/archive/refs/tags/v0.9.4.tar.gz
Platform: UNKNOWN
Classifier: Programming Language :: Python :: 3
Classifier: License :: OSI Approved :: GNU General Public License v3 or later (GPLv3+)
Classifier: Operating System :: OS Independent
Requires-Python: >=3.6
License-File: LICENSE
